chuck_says/__init__.py
chuck_says/assets/curated_facts
chuck_says/cli.py
chuck_says/cowsay.py
chuck_says-0.1.1.dist-info/entry_points.txt
chuck_says-0.1.1.dist-info/LICENSE.md
chuck_says-0.1.1.dist-info/WHEEL
chuck_says-0.1.1.dist-info/METADATA
chuck_says-0.1.1.dist-info/RECORD
