Metadata-Version: 2.1
Name: chuck-says
Version: 0.1.1
Summary: Cowsay Chuck Norris Facts
Home-page: https://franccesco.github.io/chuck-says
License: MIT
Keywords: chuck,chuck norris,cowsay,fortune
Author: Franccesco Orozco
Author-email: franccesco@codingdose.info
Requires-Python: >=3.7,<4.0
Classifier: License :: OSI Approved :: MIT License
Classifier: Programming Language :: Python :: 3
Classifier: Programming Language :: Python :: 3.7
Requires-Dist: click (>=7.0,<8.0)
Requires-Dist: requests (>=2.22,<3.0)
Project-URL: Repository, https://github.com/franccesco/chuck-says
